README.md
requirements.txt
setup.py
chainer_addons/__init__.py
chainer_addons.egg-info/PKG-INFO
chainer_addons.egg-info/SOURCES.txt
chainer_addons.egg-info/dependency_links.txt
chainer_addons.egg-info/not-zip-safe
chainer_addons.egg-info/requires.txt
chainer_addons.egg-info/top_level.txt
chainer_addons/dataset/__init__.py
chainer_addons/dataset/iterator.py
chainer_addons/functions/__init__.py
chainer_addons/functions/alpha_prod.py
chainer_addons/functions/bilinear_pooling.py
chainer_addons/functions/signed_square_root.py
chainer_addons/functions/tf_avg_pooling.py
chainer_addons/functions/fisher_encoding/__init__.py
chainer_addons/functions/fisher_encoding/base.py
chainer_addons/functions/fisher_encoding/fv_encoding.py
chainer_addons/functions/fisher_encoding/gamma.py
chainer_addons/links/__init__.py
chainer_addons/links/observable_linear.py
chainer_addons/links/fisher_encoding/__init__.py
chainer_addons/links/fisher_encoding/fv_layer.py
chainer_addons/links/fisher_encoding/gmm_layer.py
chainer_addons/links/fisher_encoding/mixtures/__init__.py
chainer_addons/links/fisher_encoding/mixtures/base.py
chainer_addons/links/fisher_encoding/mixtures/baysian.py
chainer_addons/links/fisher_encoding/mixtures/gaussian.py
chainer_addons/links/pooling/__init__.py
chainer_addons/links/pooling/alpha_pooling.py
chainer_addons/links/pooling/compact_bilinear.py
chainer_addons/links/pooling/global_avg.py
chainer_addons/models/__init__.py
chainer_addons/models/alexnet.py
chainer_addons/models/base.py
chainer_addons/models/classifier.py
chainer_addons/models/efficientnet.py
chainer_addons/models/resnet.py
chainer_addons/models/vgg.py
chainer_addons/models/inception/__init__.py
chainer_addons/models/inception/blocks.py
chainer_addons/models/inception/link_mappings.py
chainer_addons/models/inception/test.py
chainer_addons/models/inception/decoder/__init__.py
chainer_addons/models/inception/decoder/blocks.py
chainer_addons/training/__init__.py
chainer_addons/training/optimizer.py
chainer_addons/training/optimizer_hooks.py
chainer_addons/training/sacred.py
chainer_addons/training/updater.py
chainer_addons/training/extensions/__init__.py
chainer_addons/training/extensions/alternate_trainable.py
