Metadata-Version: 1.2
Name: chainer-addons
Version: 0.10.0
Summary: Some addon scripts for the chainer framework
Home-page: UNKNOWN
Author: Dimitri Korsch
Author-email: korschdima@gmail.com
License: MIT License
Platform: UNKNOWN
Requires-Python: >3.5
